LICENSE
MANIFEST.in
README.md
setup.cfg
setup.py
bin/screwjack
screwjack/__init__.py
screwjack.egg-info/PKG-INFO
screwjack.egg-info/SOURCES.txt
screwjack.egg-info/dependency_links.txt
screwjack.egg-info/requires.txt
screwjack.egg-info/top_level.txt
screwjack/misc_templates/draw_spec_json.dot.j2
screwjack/templates/basic/Dockerfile.j2
screwjack/templates/basic/main.py.j2
screwjack/templates/basic/requirements.txt.j2
screwjack/templates/basic/spec.json.j2
screwjack/templates/basic/test.sh.j2
screwjack/templates/emr_hive/Dockerfile.j2
screwjack/templates/emr_hive/main.hql.j2
screwjack/templates/emr_hive/main.py.j2
screwjack/templates/emr_hive/requirements.txt.j2
screwjack/templates/emr_hive/spec.json.j2
screwjack/templates/emr_hive/test.sh.j2
screwjack/templates/emr_jar/Dockerfile.j2
screwjack/templates/emr_jar/main.py.j2
screwjack/templates/emr_jar/requirements.txt.j2
screwjack/templates/emr_jar/spec.json.j2
screwjack/templates/emr_jar/test.sh.j2
screwjack/templates/emr_pig/Dockerfile.j2
screwjack/templates/emr_pig/main.pig.j2
screwjack/templates/emr_pig/main.py.j2
screwjack/templates/emr_pig/requirements.txt.j2
screwjack/templates/emr_pig/spec.json.j2
screwjack/templates/emr_pig/test.sh.j2
screwjack/templates/hive/Dockerfile.j2
screwjack/templates/hive/main.hql.j2
screwjack/templates/hive/main.py.j2
screwjack/templates/hive/requirements.txt.j2
screwjack/templates/hive/spec.json.j2
screwjack/templates/hive/test.sh.j2
screwjack/templates/pig/Dockerfile.j2
screwjack/templates/pig/main.pig.j2
screwjack/templates/pig/main.py.j2
screwjack/templates/pig/requirements.txt.j2
screwjack/templates/pig/spec.json.j2
screwjack/templates/pig/test.sh.j2
screwjack/templates/r/Dockerfile.j2
screwjack/templates/r/install_packages.R.j2
screwjack/templates/r/main.R.j2
screwjack/templates/r/spec.json.j2
screwjack/templates/spark/Dockerfile.j2
screwjack/templates/spark/main.py.j2
screwjack/templates/spark/requirements.txt.j2
screwjack/templates/spark/spec.json.j2
screwjack/templates/spark/test.sh.j2