Metadata-Version: 1.1
Name: screwjack
Version: 0.4.3
Summary: ScrewJack is a tiny command line tool for manipulating modules.
Home-page: https://github.com/DataCanvasIO/screwjack
Author: Xiaolin Zhang
Author-email: leoncamel@gmail.com
License: BSD
Platform: UNKNOWN
Classifier: Development Status :: 2 - Pre-Alpha
Classifier: Environment :: Console
Classifier: License :: OSI Approved :: BSD License
Classifier: Operating System :: OS Independent
Classifier: Programming Language :: Python :: 2.7
Classifier: Topic :: Utilities
